zibuyu_llm_api/__init__.py
zibuyu_llm_api/minmax_api.py
zibuyu_llm_web/__init__.py
zibuyu_llm_web/baichuan.py
zibuyu_llm_web/base.py
zibuyu_llm_web/deepseek.py
zibuyu_llm_web/emohaa.py
zibuyu_llm_web/errors.py
zibuyu_llm_web/kimi.py
zibuyu_llm_web/metaso.py
zibuyu_llm_web/minmax.py
zibuyu_llm_web/qwen.py
zibuyu_llm_web/step_chat.py
zibuyu_llm_web/types.py
zibuyu_llm_web/wanxiang.py
zibuyu_llm_web/xinchen.py
zibuyu_llm_web/xunfei.py
zibuyu_llm-2.2.26.dist-info/METADATA
zibuyu_llm-2.2.26.dist-info/WHEEL
zibuyu_llm-2.2.26.dist-info/top_level.txt
zibuyu_llm-2.2.26.dist-info/RECORD
