Metadata-Version: 2.1
Name: zibuyu_llm
Version: 2.2.26
Summary: 子不语个人工具包-LLM
Author: 子不语
License: MIT
Keywords: zibuyu
Classifier: License :: OSI Approved :: MIT License
Classifier: Operating System :: OS Independent
Classifier: Intended Audience :: Developers
Classifier: Programming Language :: Python :: 3.9
Classifier: Programming Language :: Python :: 3.10
Classifier: Programming Language :: Python :: 3.11
Classifier: Programming Language :: Python :: 3.12
Requires-Python: >=3.9
Requires-Dist: certifi
Requires-Dist: charset-normalizer
Requires-Dist: fake-useragent
Requires-Dist: filetype
Requires-Dist: idna
Requires-Dist: importlib-resources
Requires-Dist: requests
Requires-Dist: urllib3
Requires-Dist: zipp
Requires-Dist: aiohttp
Requires-Dist: ddddocr
Requires-Dist: beautifulsoup4
Requires-Dist: numpy
Requires-Dist: Pillow
